odoo/addons/crm_l10n_eu_nace/README.rst
odoo/addons/crm_l10n_eu_nace/__init__.py
odoo/addons/crm_l10n_eu_nace/__manifest__.py
odoo/addons/crm_l10n_eu_nace/i18n/crm_l10n_eu_nace.pot
odoo/addons/crm_l10n_eu_nace/i18n/es.po
odoo/addons/crm_l10n_eu_nace/i18n/it.po
odoo/addons/crm_l10n_eu_nace/models/__init__.py
odoo/addons/crm_l10n_eu_nace/models/crm_lead.py
odoo/addons/crm_l10n_eu_nace/readme/CONTRIBUTORS.rst
odoo/addons/crm_l10n_eu_nace/readme/DESCRIPTION.rst
odoo/addons/crm_l10n_eu_nace/readme/INSTALL.rst
odoo/addons/crm_l10n_eu_nace/static/description/icon.png
odoo/addons/crm_l10n_eu_nace/static/description/index.html
odoo/addons/crm_l10n_eu_nace/tests/__init__.py
odoo/addons/crm_l10n_eu_nace/tests/test_crm_nace.py
odoo/addons/crm_l10n_eu_nace/views/crm_lead_view.xml
odoo12_addon_crm_l10n_eu_nace-12.0.1.0.0.99.dev6.dist-info/METADATA
odoo12_addon_crm_l10n_eu_nace-12.0.1.0.0.99.dev6.dist-info/WHEEL
odoo12_addon_crm_l10n_eu_nace-12.0.1.0.0.99.dev6.dist-info/top_level.txt
odoo12_addon_crm_l10n_eu_nace-12.0.1.0.0.99.dev6.dist-info/RECORD
